deepface_antispoofing/__init__.py
deepface_antispoofing-1.1.3.dist-info/METADATA
deepface_antispoofing-1.1.3.dist-info/WHEEL
deepface_antispoofing-1.1.3.dist-info/top_level.txt
deepface_antispoofing-1.1.3.dist-info/RECORD
