Metadata-Version: 2.4
Name: deepface-antispoofing
Version: 1.1.3
Summary: A comprehensive Python package for advanced face recognition, anti-spoofing, deepfake detection, emotion analysis, and face mask detection. Offers robust analysis to distinguish real faces from printed images, replay attacks, and presentation attacks, alongside precise age, gender, emotion, mask status, and genuine vs. AI-generated face predictions. Ideal for secure authentication and identity verification systems.
Author: IP Softech - Pratham Pansuriya
Author-email: ipsoftechsolutions@gmail.com
Classifier: Programming Language :: Python
Classifier: License :: OSI Approved :: MIT License
Classifier: Operating System :: OS Independent
Requires-Python: >=3.10
Requires-Dist: requests
Requires-Dist: opencv-python
Requires-Dist: numpy
Requires-Dist: tensorflow
Requires-Dist: flask
Requires-Dist: flask-cors
Dynamic: author
Dynamic: author-email
Dynamic: classifier
Dynamic: description
Dynamic: description-content-type
Dynamic: requires-dist
Dynamic: requires-python
Dynamic: summary
